sqlite_database/__init__.py
sqlite_database/_debug.py
sqlite_database/_utils.py
sqlite_database/column.py
sqlite_database/csv.py
sqlite_database/database.py
sqlite_database/errors.py
sqlite_database/functions.py
sqlite_database/locals.py
sqlite_database/operators.py
sqlite_database/query_builder.py
sqlite_database/signature.py
sqlite_database/subquery.py
sqlite_database/table.py
sqlite_database/typings.py
sqlite_database/utils.py
sqlite_database/models/__init__.py
sqlite_database/models/errors.py
sqlite_database/models/helpers.py
sqlite_database/models/mixin.py
sqlite_database/models/query_builder.py
sqlite_database/models/type_checkers.py
sqlite_database/workers/__init__.py
sqlite_database/workers/connection.py
sqlite_database/workers/database.py
sqlite_database-0.7.11.dist-info/licenses/LICENSE
sqlite_database-0.7.11.dist-info/METADATA
sqlite_database-0.7.11.dist-info/WHEEL
sqlite_database-0.7.11.dist-info/top_level.txt
sqlite_database-0.7.11.dist-info/zip-safe
sqlite_database-0.7.11.dist-info/RECORD
