Metadata-Version: 2.4
Name: sqlite_database
Version: 0.7.11
Summary: Easy to use SQLite wrapper
Home-page: https://github.com/RimuEirnarn/sqlite_database
Author: RimuEirnarn
Author-email: Rimu Eirnarn <rimuru720@proton.me>
License-Expression: BSD-3-Clause
Project-URL: Homepage, https://github.com/RimuEirnarn/sqlite_database
Project-URL: Documentation, https://sqlite-database.rtfd.io
Project-URL: Repository, https://github.com/RimuEirnarn/sqlite_database.git
Keywords: sqlite,sqlite3
Classifier: Programming Language :: Python :: 3.11
Classifier: Programming Language :: Python :: Implementation :: CPython
Requires-Python: >=3.11
License-File: LICENSE
Provides-Extra: dev
Requires-Dist: pytest; extra == "dev"
Requires-Dist: pylint; extra == "dev"
Requires-Dist: black; extra == "dev"
Provides-Extra: docs
Requires-Dist: sphinx; extra == "docs"
Requires-Dist: myst_parser; extra == "docs"
Dynamic: license-file
